mqlparser/__init__.py
mqlparser/parser.py
mqlparser/util.py
mqlparser-0.1.dist-info/DESCRIPTION.rst
mqlparser-0.1.dist-info/METADATA
mqlparser-0.1.dist-info/metadata.json
mqlparser-0.1.dist-info/namespace_packages.txt
mqlparser-0.1.dist-info/RECORD
mqlparser-0.1.dist-info/top_level.txt
mqlparser-0.1.dist-info/WHEEL
tests/__init__.py
tests/test_parser.py
