Metadata-Version: 2.0
Name: mqlparser
Version: 0.1
Summary: Parser for MQL queries
Home-page: http://github.com/pudo/mqlparser
Author: Friedrich Lindenberg
Author-email: friedrich@pudo.org
License: MIT
Keywords: mql metaweb freebase
Platform: UNKNOWN
Classifier: Development Status :: 3 - Alpha
Classifier: Intended Audience :: Developers
Classifier: License :: OSI Approved :: MIT License
Classifier: Operating System :: OS Independent
Classifier: Programming Language :: Python :: 2.6
Classifier: Programming Language :: Python :: 2.7
Classifier: Programming Language :: Python :: 3.3
Classifier: Programming Language :: Python :: 3.4
Requires-Dist: six
